{
  "result": {
    "status": 200,
    "retcount": 1,
    "errcd": null,
    "errmsg": null,
    "function": "外部公開用最新ファンド情報（指定ファンド）"
  },
  "errors": {
    "count": 0,
    "error_list": null
  },
  "datasets": [
    {
      "fund_cd": "253266",
      "isin_cd": "JP90C000GKC6",
      "association_fund_cd": "03311187",
      "base_date": "20251128",
      "fund_name": "ｅＭＡＸＩＳ Ｓｌｉｍ 米国株式（Ｓ＆Ｐ５００）",
      "nav": 38984,
      "cmp_prev_day": "179",
      "percentage_change": "0.46",
      "cancellation_price": 38984,
      "netassets": 9537343707604,
      "netassets_change_cmp_prev_day": "0.48",
      "percentage_change_1m": "1.6",
      "percentage_change_3m": "11.98",
      "percentage_change_6m": "26.08",
      "percentage_change_1y": "19.24",
      "percentage_change_3y": "101.16",
      "percentage_change_full": "289.84",
      "percentage_change_max_1m": "6.07",
      "percentage_change_max_3m": "15.14",
      "percentage_change_max_6m": "43.14",
      "percentage_change_max_1y": "42.15",
      "percentage_change_max_3y": "116.79",
      "percentage_change_max_full": "289.84",
      "percentage_change_min_1m": "0.5",
      "percentage_change_min_3m": "7.3",
      "percentage_change_min_6m": "-6.82",
      "percentage_change_min_1y": "-7.38",
      "percentage_change_min_3y": "33.59",
      "percentage_change_min_full": "-15.68",
      "risk_1y": "23.27",
      "risk_3y": "19.5",
      "risk_full": "22.63",
      "risk_return_1y": "0.86",
      "risk_return_3y": "1.38",
      "risk_return_full": "0.91",
      "nav_max_1m": "38984",
      "nav_max_1m_dt": "20251128",
      "nav_max_3m": "38984",
      "nav_max_3m_dt": "20251128",
      "nav_max_6m": "38984",
      "nav_max_6m_dt": "20251128",
      "nav_max_1y": "38984",
      "nav_max_1y_dt": "20251128",
      "nav_max_3y": "38984",
      "nav_max_3y_dt": "20251128",
      "nav_max_full": "38984",
      "nav_max_full_dt": "20251128",
      "nav_min_1m": "37592",
      "nav_min_1m_dt": "20251107",
      "nav_min_3m": "34677",
      "nav_min_3m_dt": "20250901",
      "nav_min_6m": "30825",
      "nav_min_6m_dt": "20250603",
      "nav_min_1y": "26296",
      "nav_min_1y_dt": "20250409",
      "nav_min_3y": "17690",
      "nav_min_3y_dt": "20230104",
      "nav_min_full": "8432",
      "nav_min_full_dt": "20200324"
    }
  ]
}